PhrameAPI/__init__.py
PhrameAPI/api_client.py
PhrameAPI/api_response.py
PhrameAPI/configuration.py
PhrameAPI/exceptions.py
PhrameAPI/py.typed
PhrameAPI/rest.py
PhrameAPI/api/__init__.py
PhrameAPI/api/phrame_api.py
PhrameAPI/models/__init__.py
PhrameAPI/models/db_phrame_json_store.py
PhrameAPI/models/db_phrame_ui_configuration.py
phrameapi-1.1.5.dist-info/licenses/LICENSE
phrameapi-1.1.5.dist-info/METADATA
phrameapi-1.1.5.dist-info/WHEEL
phrameapi-1.1.5.dist-info/top_level.txt
phrameapi-1.1.5.dist-info/RECORD
