Metadata-Version: 2.4
Name: PhrameAPI
Version: 1.1.5
Summary: Phrame API
Home-page: 
Author: David Atkins
Author-email: Gustav Rodel <gustav.rodel@3adesign.co.uk>, David Atkins <david@3adesign.co.uk>, Max Smith <max.smith@3adesign.co.uk>
License: Copyright © 2025 3ADesign Limited
Keywords: OpenAPI,OpenAPI-Generator,PhrameAPI
Classifier: License :: OSI Approved :: MIT License
Classifier: Programming Language :: Python
Classifier: Programming Language :: Python :: 3
Requires-Python: >=3.4
License-File: LICENSE
Requires-Dist: connexion>=2.0.2
Requires-Dist: swagger-ui-bundle>=0.0.2
Requires-Dist: python_dateutil>=2.6.0
Requires-Dist: setuptools>=21.0.0
Requires-Dist: requests
Requires-Dist: pydantic
Requires-Dist: opentelemetry.sdk
Requires-Dist: opentelemetry.api
Requires-Dist: opentelemetry-instrumentation
Requires-Dist: opentelemetry.instrumentation.urllib3
Dynamic: author
Dynamic: license-file
